ppt_translator/__init__.py
ppt_translator/bedrock_client.py
ppt_translator/cli.py
ppt_translator/config.py
ppt_translator/dependencies.py
ppt_translator/post_processing.py
ppt_translator/ppt_handler.py
ppt_translator/prompts.py
ppt_translator/text_utils.py
ppt_translator/translation_engine.py
ppt_translator-0.1.0.dist-info/METADATA
ppt_translator-0.1.0.dist-info/WHEEL
ppt_translator-0.1.0.dist-info/entry_points.txt
ppt_translator-0.1.0.dist-info/licenses/LICENSE
ppt_translator-0.1.0.dist-info/RECORD
