Metadata-Version: 2.4
Name: ppt-translator
Version: 0.1.0
Summary: AI-powered PowerPoint presentation translator using Amazon Bedrock
Project-URL: Homepage, https://github.com/your-org/ppt-translator
Project-URL: Documentation, https://github.com/your-org/ppt-translator#readme
Project-URL: Repository, https://github.com/your-org/ppt-translator.git
Project-URL: Issues, https://github.com/your-org/ppt-translator/issues
Project-URL: Changelog, https://github.com/your-org/ppt-translator/blob/main/CHANGELOG.md
Author-email: PPT-Translator Team <contact@ppt-translator.com>
Maintainer-email: PPT-Translator Team <contact@ppt-translator.com>
License: MIT License
License-File: LICENSE
Keywords: ai,bedrock,powerpoint,ppt,presentation,translation
Classifier: Development Status :: 4 - Beta
Classifier: Intended Audience :: Developers
Classifier: Intended Audience :: End Users/Desktop
Classifier: License :: OSI Approved :: MIT License
Classifier: Operating System :: OS Independent
Classifier: Programming Language :: Python :: 3
Classifier: Programming Language :: Python :: 3.11
Classifier: Programming Language :: Python :: 3.12
Classifier: Programming Language :: Python :: 3.13
Classifier: Topic :: Office/Business :: Office Suites
Classifier: Topic :: Text Processing :: Linguistic
Classifier: Topic :: Utilities
Requires-Python: >=3.11
Requires-Dist: boto3>=1.40.1
Requires-Dist: fastapi>=0.116.1
Requires-Dist: fastmcp>=2.11.0
Requires-Dist: python-dotenv>=1.1.1
Requires-Dist: python-multipart>=0.0.20
Requires-Dist: python-pptx>=1.0.2
Requires-Dist: uvicorn>=0.35.0
Provides-Extra: dev
Requires-Dist: black>=23.0.0; extra == 'dev'
Requires-Dist: flake8>=6.0.0; extra == 'dev'
Requires-Dist: isort>=5.12.0; extra == 'dev'
Requires-Dist: mypy>=1.0.0; extra == 'dev'
Requires-Dist: pytest-cov>=4.0.0; extra == 'dev'
Requires-Dist: pytest>=7.0.0; extra == 'dev'
Provides-Extra: gui
Requires-Dist: tkinter-tooltip>=2.0.0; extra == 'gui'
Provides-Extra: web
Requires-Dist: fastapi>=0.104.0; extra == 'web'
Requires-Dist: python-multipart>=0.0.6; extra == 'web'
Requires-Dist: uvicorn>=0.24.0; extra == 'web'
